docs/conf.py
pdfhandler/__init__.py
pdfhandler/__main__.py
pdfhandler/pdf_handler.py
pdfhandler/tests/test_cli.py
pdfhandler/tests/test_pdf_helper.py
pdfhandleretc-0.1.4.dist-info/licenses/LICENSE
pdfhandleretc-0.1.4.dist-info/METADATA
pdfhandleretc-0.1.4.dist-info/WHEEL
pdfhandleretc-0.1.4.dist-info/entry_points.txt
pdfhandleretc-0.1.4.dist-info/top_level.txt
pdfhandleretc-0.1.4.dist-info/RECORD
