Metadata-Version: 2.4
Name: pdfhandleretc
Version: 0.1.4
Summary: Lightweight command-line and Python API toolkit for PDF text extraction, encryption, permissions, and more.
Author-email: "E. Tyler Carr" <carret1268@gmail.com>
License: CC0-1.0
Project-URL: Homepage, https://github.com/carret1268/pdfhandleretc
Project-URL: Repository, https://github.com/carret1268/pdfhandleretc
Project-URL: Issues, https://github.com/carret1268/pdfhandleretc/issues
Keywords: pdf,pdfminer,pikepdf,encryption,text-extraction,cli
Classifier: Programming Language :: Python :: 3
Classifier: License :: CC0 1.0 Universal (CC0 1.0) Public Domain Dedication
Classifier: Operating System :: OS Independent
Classifier: Topic :: Text Processing :: General
Classifier: Topic :: Utilities
Requires-Python: >=3.10
License-File: LICENSE
Requires-Dist: pdfminer.six>=20221105
Requires-Dist: pikepdf>=7.0.0
Requires-Dist: colorama>=0.4.6
Provides-Extra: dev
Requires-Dist: ruff; extra == "dev"
Requires-Dist: mypy; extra == "dev"
Requires-Dist: sphinx; extra == "dev"
Requires-Dist: sphinx_autodoc_typehints; extra == "dev"
Requires-Dist: furo; extra == "dev"
Requires-Dist: myst_parser; extra == "dev"
Requires-Dist: build; extra == "dev"
Requires-Dist: coverage; extra == "dev"
Dynamic: license-file
